Docgen.py
postoi_docgen-0.1.3.dist-info/METADATA
postoi_docgen-0.1.3.dist-info/WHEEL
postoi_docgen-0.1.3.dist-info/top_level.txt
postoi_docgen-0.1.3.dist-info/RECORD
