Metadata-Version: 2.4
Name: postoi-docgen
Version: 0.1.3
Summary: Generate documents from templates
License: MIT
Classifier: Programming Language :: Python :: 3
Classifier: License :: OSI Approved :: MIT License
Classifier: Operating System :: OS Independent
Requires-Python: >=3.10
Requires-Dist: babel<2.10.1
Requires-Dist: docxcompose==1.4.0
Requires-Dist: docxtpl==0.16.6
Requires-Dist: jinja2==3.1.2
Requires-Dist: lxml==4.9.2
Requires-Dist: markupsafe==2.1.2
Requires-Dist: python-docx==0.8.11
Requires-Dist: six==1.16.0
